{"hitCount": 1, "request": {"cursorMark": "*", "pageSize": 1, "queryString": "DOI:\"10.1016/j.watres.2006.01.038\"", "resultType": "core", "sort": "", "synonym": false}, "resultList": {"result": [{"abstractText": "The potential of nanofiltration for the separation of pharmaceutical and estrogenic compounds from salts in urine was investigated with the aim of producing a micropollutant-free nutrient solution that can be used as a fertilizer. A fresh urine solution and a synthetic solution of similar inorganic composition were tested at different pH values in order to investigate their separation behavior. These solutions were spiked with the micropollutants propranolol, ethinylestradiol, ibuprofen, diclofenac and carbamazepine. Among the membranes tested, NF270 showed the best performance with respect to the retention of micropollutants. The optimum retention of micropollutants was obtained at values of around pH 5. At this point, the retention of all micropollutants in non-hydrolysed urine was above 92%, while the corresponding value for the synthetic urine solution was above 73%. From the results, it can be concluded that the retention mechanism is determined by steric and electrostatic effects as well as by the partitioning of the micropollutants in the membrane. The nutrients urea and ammonia were well permeated, but phosphate and sulfate were almost completely retained. Nanofiltration can consequently be used to produce a permeate which contains most of the nitrogen and a greatly reduced proportion of micropollutants.", "affiliation": "Eawag Aquatic Research, P.O. Box 611, CH-8600 Dübendorf, Switzerland. wouter.pronk@eawag.ch", "authMan": "N", "authorList": {"author": [{"authorAffiliationDetailsList": {"authorAffiliation": [{"affiliation": "Eawag Aquatic Research, P.O. Box 611, CH-8600 Dübendorf, Switzerland. wouter.pronk@eawag.ch"}]}, "firstName": "Wouter", "fullName": "Pronk W", "initials": "W", "lastName": "Pronk"}, {"firstName": "Helena", "fullName": "Palmquist H", "initials": "H", "lastName": "Palmquist"}, {"firstName": "Martin", "fullName": "Biebow M", "initials": "M", "lastName": "Biebow"}, {"firstName": "Markus", "fullName": "Boller M", "initials": "M", "lastName": "Boller"}]}, "authorString": "Pronk W, Palmquist H, Biebow M, Boller M.", "chemicalList": {"chemical": [{"name": "Pharmaceutical Preparations", "registryNumber": "0"}, {"name": "Water Pollutants, Chemical", "registryNumber": "0"}]}, "citedByCount": 56, "dateOfCompletion": "2006-09-14", "dateOfCreation": "2006-03-15", "dateOfRevision": "2006-03-27", "doi": "10.1016/j.watres.2006.01.038", "electronicPublicationDate": "2006-03-13", "epmcAuthMan": "N", "firstIndexDate": "2008-01-29", "firstPublicationDate": "2006-03-13", "fullTextUrlList": {"fullTextUrl": [{"availability": "Subscription required", "availabilityCode": "S", "documentStyle": "doi", "site": "DOI", "url": "https://doi.org/10.1016/j.watres.2006.01.038"}]}, "hasBook": "N", "hasData": "N", "hasDbCrossReferences": "N", "hasEvaluations": "N", "hasLabsLinks": "N", "hasPDF": "N", "hasReferences": "Y", "hasSuppl": "N", "hasTMAccessionNumbers": "N", "hasTextMinedTerms": "Y", "id": "16530802", "inEPMC": "N", "inPMC": "N", "isOpenAccess": "N", "journalInfo": {"dateOfPublication": "2006 Apr", "issue": "7", "journal": {"essn": "1879-2448", "isoabbreviation": "Water Res", "issn": "0043-1354", "medlineAbbreviation": "Water Res", "nlmid": "0105072", "title": "Water research"}, "journalIssueId": 1308972, "monthOfPublication": 4, "printPublicationDate": "2006-04-01", "volume": "40", "yearOfPublication": 2006}, "language": "eng", "meshHeadingList": {"meshHeading": [{"descriptorName": "Urine", "majorTopic_YN": "N", "meshQualifierList": {"meshQualifier": [{"abbreviation": "CH", "majorTopic_YN": "Y", "qualifierName": "chemistry"}]}}, {"descriptorName": "Pharmaceutical Preparations", "majorTopic_YN": "N", "meshQualifierList": {"meshQualifier": [{"abbreviation": "CH", "majorTopic_YN": "Y", "qualifierName": "chemistry"}]}}, {"descriptorName": "Water Pollutants, Chemical", "majorTopic_YN": "N"}, {"descriptorName": "Filtration", "majorTopic_YN": "N", "meshQualifierList": {"meshQualifier": [{"abbreviation": "IS", "majorTopic_YN": "Y", "qualifierName": "instrumentation"}, {"abbreviation": "MT", "majorTopic_YN": "N", "qualifierName": "methods"}]}}, {"descriptorName": "Waste Disposal, Fluid", "majorTopic_YN": "N", "meshQualifierList": {"meshQualifier": [{"abbreviation": "MT", "majorTopic_YN": "Y", "qualifierName": "methods"}]}}, {"descriptorName": "Molecular Structure", "majorTopic_YN": "N"}, {"descriptorName": "Hydrogen-Ion Concentration", "majorTopic_YN": "N"}, {"descriptorName": "Nanotechnology", "majorTopic_YN": "N", "meshQualifierList": {"meshQualifier": [{"abbreviation": "IS", "majorTopic_YN": "Y", "qualifierName": "instrumentation"}, {"abbreviation": "MT", "majorTopic_YN": "N", "qualifierName": "methods"}]}}]}, "nihAuthMan": "N", "pageInfo": "1405-1412", "pmid": "16530802", "pubModel": "Print-Electronic", "pubTypeList": {"pubType": ["Journal Article"]}, "pubYear": "2006", "publicationStatus": "ppublish", "source": "MED", "subsetList": {"subset": [{"code": "IM", "name": "Index Medicus"}]}, "title": "Nanofiltration for the separation of pharmaceuticals from nutrients in source-separated urine."}]}, "version": "6.9"}