{"hitCount": 1, "request": {"cursorMark": "*", "pageSize": 1, "queryString": "DOI:\"10.1007/s00216-005-3296-z\"", "resultType": "core", "sort": "", "synonym": false}, "resultList": {"result": [{"abstractText": "The separation behavior of the frequently administered pharmaceuticals sulfamethoxazol (Sulfa), carbamazepine (Carba), diclofenac (Diclo), and ibuprofen (Ibu) on different natural and synthetic ultrafiltration membranes was studied. Commercially available cattle intestine natural membranes (NM), polyethersulfone (PES), and regenerated cellulose-based (RC) flat membranes (nominal cut-off 1 kDa) have been investigated as ultrafiltration membranes in a small tangential-flow ultrafiltration unit (TF-UF). First, the nominal cut-off of the NM membranes under study was assessed at approximately 5 kDa, by using polystyrenesulfonate standards for pore-size classification at low TF-UF pressure (0.25 x 10(5) Pa). Working pressures of >1.5 x 10(5) Pa strongly increased the cut-off of NM, in contrast with that of PES and RC membranes. Sulfa, Carba, Diclo and Ibu (1 mg L(-1) each) in colloid-free aqueous solutions (400 mg L(-1) NaCl) completely permeated through NM membranes, but less through PES and RC, which had particular sorption capability towards Diclo. The drugs were routinely determined by using high-performance liquid chromatography (HPLC). Detailed TF-UF investigation of drug retention on NM in the presence of humic hydrocolloids revealed strong interactions between aquatic humic substances (HS) and Diclo and Ibu (but not with Sulfa and Carba) causing retention of up to 80% of Diclo and Ibu, probably because of their binding to macromolecular HS. The standard deviation (SD) of both drug and HS permeation through a single NM was between 2.5 (Sulfa) and 4.0% (Diclo), in contrast with the SD of permeation through separate membranes taken from different lots [SD up to 14.0% (Diclo)], presumably caused by natural variation of the studied NM. Accordingly, membrane filtration of drug-containing water samples on cattle intestines enables both analyte/matrix separations for Carba and Sulfa in the presence of humic colloids and analytical discrimination between free and colloid-bound Diclo and Ibu fractions.", "affiliation": "ISAS, Institute for Analytical Sciences, Bunsen-Kirchhoff-Str. 11, 44139 Dortmund, Germany.", "authMan": "N", "authorList": {"author": [{"authorAffiliationDetailsList": {"authorAffiliation": [{"affiliation": "ISAS, Institute for Analytical Sciences, Bunsen-Kirchhoff-Str. 11, 44139 Dortmund, Germany."}]}, "firstName": "Peter", "fullName": "Burba P", "initials": "P", "lastName": "Burba"}, {"firstName": "Helma", "fullName": "Geltenpoth H", "initials": "H", "lastName": "Geltenpoth"}, {"firstName": "Jürgen", "fullName": "Nolte J", "initials": "J", "lastName": "Nolte"}]}, "authorString": "Burba P, Geltenpoth H, Nolte J.", "chemicalList": {"chemical": [{"name": "polyether sulfone", "registryNumber": "25667-42-9"}, {"name": "Polymers", "registryNumber": "0"}, {"name": "Pharmaceutical Preparations", "registryNumber": "0"}, {"name": "Cellulose", "registryNumber": "9004-34-6"}, {"name": "Sulfones", "registryNumber": "0"}, {"name": "Colloids", "registryNumber": "0"}, {"name": "Humic Substances", "registryNumber": "0"}, {"name": "Membranes, Artificial", "registryNumber": "0"}, {"name": "Carbamazepine", "registryNumber": "33CM23913M"}, {"name": "Diclofenac", "registryNumber": "144O8QL0L1"}, {"name": "Ibuprofen", "registryNumber": "WK2XYI10QM"}, {"name": "Sulfamethoxazole", "registryNumber": "JE42381TNV"}]}, "citedByCount": 2, "dataLinksTagsList": {"dataLinkstag": ["altmetrics"]}, "dateOfCompletion": "2005-11-10", "dateOfCreation": "2005-07-16", "dateOfRevision": "2016-05-12", "doi": "10.1007/s00216-005-3296-z", "electronicPublicationDate": "2005-07-15", "epmcAuthMan": "N", "firstIndexDate": "2008-01-29", "firstPublicationDate": "2005-07-15", "fullTextUrlList": {"fullTextUrl": [{"availability": "Subscription required", "availabilityCode": "S", "documentStyle": "doi", "site": "DOI", "url": "https://doi.org/10.1007/s00216-005-3296-z"}]}, "hasBook": "N", "hasData": "N", "hasDbCrossReferences": "N", "hasEvaluations": "N", "hasLabsLinks": "Y", "hasPDF": "N", "hasReferences": "Y", "hasSuppl": "N", "hasTMAccessionNumbers": "N", "hasTextMinedTerms": "Y", "id": "16021427", "inEPMC": "N", "inPMC": "N", "isOpenAccess": "N", "journalInfo": {"dateOfPublication": "2005 Aug", "issue": "8", "journal": {"essn": "1618-2650", "isoabbreviation": "Anal Bioanal Chem", "issn": "1618-2642", "medlineAbbreviation": "Anal Bioanal Chem", "nlmid": "101134327", "title": "Analytical and bioanalytical chemistry"}, "journalIssueId": 1257156, "monthOfPublication": 8, "printPublicationDate": "2005-08-01", "volume": "382", "yearOfPublication": 2005}, "language": "eng", "meshHeadingList": {"meshHeading": [{"descriptorName": "Intestinal Mucosa", "majorTopic_YN": "N", "meshQualifierList": {"meshQualifier": [{"abbreviation": "CY", "majorTopic_YN": "N", "qualifierName": "cytology"}, {"abbreviation": "CH", "majorTopic_YN": "N", "qualifierName": "chemistry"}]}}, {"descriptorName": "Cell Membrane", "majorTopic_YN": "N", "meshQualifierList": {"meshQualifier": [{"abbreviation": "CH", "majorTopic_YN": "Y", "qualifierName": "chemistry"}]}}, {"descriptorName": "Animals", "majorTopic_YN": "N"}, {"descriptorName": "Cattle", "majorTopic_YN": "N"}, {"descriptorName": "Sulfamethoxazole", "majorTopic_YN": "N", "meshQualifierList": {"meshQualifier": [{"abbreviation": "ME", "majorTopic_YN": "N", "qualifierName": "metabolism"}, {"abbreviation": "CH", "majorTopic_YN": "N", "qualifierName": "chemistry"}]}}, {"descriptorName": "Diclofenac", "majorTopic_YN": "N", "meshQualifierList": {"meshQualifier": [{"abbreviation": "CH", "majorTopic_YN": "N", "qualifierName": "chemistry"}]}}, {"descriptorName": "Ibuprofen", "majorTopic_YN": "N", "meshQualifierList": {"meshQualifier": [{"abbreviation": "CH", "majorTopic_YN": "N", "qualifierName": "chemistry"}]}}, {"descriptorName": "Humic Substances", "majorTopic_YN": "Y"}, {"descriptorName": "Sulfones", "majorTopic_YN": "N", "meshQualifierList": {"meshQualifier": [{"abbreviation": "CH", "majorTopic_YN": "N", "qualifierName": "chemistry"}]}}, {"descriptorName": "Carbamazepine", "majorTopic_YN": "N", "meshQualifierList": {"meshQualifier": [{"abbreviation": "ME", "majorTopic_YN": "N", "qualifierName": "metabolism"}, {"abbreviation": "CH", "majorTopic_YN": "N", "qualifierName": "chemistry"}]}}, {"descriptorName": "Polymers", "majorTopic_YN": "N", "meshQualifierList": {"meshQualifier": [{"abbreviation": "CH", "majorTopic_YN": "N", "qualifierName": "chemistry"}]}}, {"descriptorName": "Cellulose", "majorTopic_YN": "N", "meshQualifierList": {"meshQualifier": [{"abbreviation": "CH", "majorTopic_YN": "N", "qualifierName": "chemistry"}]}}, {"descriptorName": "Membranes, Artificial", "majorTopic_YN": "Y"}, {"descriptorName": "Pharmaceutical Preparations", "majorTopic_YN": "N", "meshQualifierList": {"meshQualifier": [{"abbreviation": "ME", "majorTopic_YN": "N", "qualifierName": "metabolism"}, {"abbreviation": "CH", "majorTopic_YN": "Y", "qualifierName": "chemistry"}]}}, {"descriptorName": "Colloids", "majorTopic_YN": "N", "meshQualifierList": {"meshQualifier": [{"abbreviation": "CH", "majorTopic_YN": "Y", "qualifierName": "chemistry"}]}}, {"descriptorName": "Ultrafiltration", "majorTopic_YN": "N", "meshQualifierList": {"meshQualifier": [{"abbreviation": "MT", "majorTopic_YN": "Y", "qualifierName": "methods"}]}}, {"descriptorName": "Molecular Structure", "majorTopic_YN": "N"}]}, "nihAuthMan": "N", "pageInfo": "1934-1941", "pmid": "16021427", "pubModel": "Print-Electronic", "pubTypeList": {"pubType": ["Research Support, Non-U.S. Gov't", "Journal Article"]}, "pubYear": "2005", "publicationStatus": "ppublish", "source": "MED", "subsetList": {"subset": [{"code": "IM", "name": "Index Medicus"}]}, "title": "Ultrafiltration behavior of selected pharmaceuticals on natural and synthetic membranes in the presence of humic-rich hydrocolloids."}]}, "version": "6.9"}