{"hitCount": 1, "request": {"cursorMark": "*", "pageSize": 1, "queryString": "DOI:\"10.1080/713840406\"", "resultType": "core", "sort": "", "synonym": false}, "resultList": {"result": [{"abstractText": "To improve the solubility and in vitro dissolution of poorly water-soluble ibuprofen with poloxamer and menthol, the effects of menthol and poloxamer 188 on the aqueous solubility of ibuprofen were investigated. The dissolution study of ibuprofen delivered by poloxamer gels composed of poloxamer 188 and menthol were performed. In the absence of poloxamer, the solubility of ibuprofen increased until the ratio of menthol to ibuprofen increased from 0:10 to 4:6, followed by an abrupt decrease in solubility above the ratio of 4:6, indicating that 4 parts of ibuprofen formed eutectic mixture with 6 parts of menthol. In the presence of poloxamer 188, the solutions with the same ratio of menthol to ibuprofen showed abrupt increase in the solubility of ibuprofen. Furthermore, the solution with ratio of 4:6 showed more than 2.5- and 6-fold increase in the solubility of ibuprofen compared with that without poloxamer and that without menthol, respectively. The poloxamer gel with menthol/ibuprofen ratio of 1:9 and higher than 15% poloxamer 188 showed the maximum solubility of ibuprofen, 1.2 mg/ml. Menthol improved the dissolution rates of ibuprofen from poloxamer gels. Dissolution mechanism showed that the dissolution rate of ibuprofen from the poloxamer gels without menthol was independent of the time, but the drug might be dissolved from the poloxamer gels with menthol by Fickian diffusion. Thus, the poloxamer gels developed using eutectic mixture with menthol, which gave the improved solubility and dissolution of drug, are potential candidates for ibuprofen-loaded transdermal and rectal delivery system.", "affiliation": "College of Pharmacy, Yeungnam University, Gyongsan, South Korea.", "authMan": "N", "authorList": {"author": [{"authorAffiliationDetailsList": {"authorAffiliation": [{"affiliation": "College of Pharmacy, Yeungnam University, Gyongsan, South Korea."}]}, "firstName": "Chul Soon", "fullName": "Yong CS", "initials": "CS", "lastName": "Yong"}, {"firstName": "Se Hyun", "fullName": "Jung SH", "initials": "SH", "lastName": "Jung"}, {"firstName": "Jong-Dal", "fullName": "Rhee JD", "initials": "JD", "lastName": "Rhee"}, {"firstName": "Han-Gon", "fullName": "Choi HG", "initials": "HG", "lastName": "Choi"}, {"firstName": "Beom-Jin", "fullName": "Lee BJ", "initials": "BJ", "lastName": "Lee"}, {"firstName": "Dong-Chool", "fullName": "Kim DC", "initials": "DC", "lastName": "Kim"}, {"firstName": "Young Wook", "fullName": "Choi YW", "initials": "YW", "lastName": "Choi"}, {"firstName": "Chong-Kook", "fullName": "Kim CK", "initials": "CK", "lastName": "Kim"}]}, "authorString": "Yong CS, Jung SH, Rhee JD, Choi HG, Lee BJ, Kim DC, Choi YW, Kim CK.", "chemicalList": {"chemical": [{"name": "Anti-Inflammatory Agents, Non-Steroidal", "registryNumber": "0"}, {"name": "Gels", "registryNumber": "0"}, {"name": "Menthol", "registryNumber": "1490-04-6"}, {"name": "Poloxamer", "registryNumber": "106392-12-5"}, {"name": "Ibuprofen", "registryNumber": "WK2XYI10QM"}]}, "citedByCount": 11, "dataLinksTagsList": {"dataLinkstag": ["altmetrics"]}, "dateOfCompletion": "2004-05-21", "dateOfCreation": "2003-08-29", "dateOfRevision": "2019-05-16", "doi": "10.1080/713840406", "epmcAuthMan": "N", "firstIndexDate": "2008-01-29", "firstPublicationDate": "2003-07-01", "fullTextUrlList": {"fullTextUrl": [{"availability": "Subscription required", "availabilityCode": "S", "documentStyle": "doi", "site": "DOI", "url": "https://doi.org/10.1080/713840406"}]}, "hasBook": "N", "hasData": "N", "hasDbCrossReferences": "N", "hasEvaluations": "N", "hasLabsLinks": "Y", "hasPDF": "N", "hasReferences": "N", "hasSuppl": "N", "hasTMAccessionNumbers": "N", "hasTextMinedTerms": "Y", "id": "12944138", "inEPMC": "N", "inPMC": "N", "isOpenAccess": "N", "journalInfo": {"dateOfPublication": "2003 Jul-Sep", "issue": "3", "journal": {"essn": "1521-0464", "isoabbreviation": "Drug Deliv", "issn": "1071-7544", "medlineAbbreviation": "Drug Deliv", "nlmid": "9417471", "title": "Drug delivery"}, "journalIssueId": 1148668, "monthOfPublication": 0, "printPublicationDate": "2003-07-01", "volume": "10", "yearOfPublication": 2003}, "language": "eng", "meshHeadingList": {"meshHeading": [{"descriptorName": "Poloxamer", "majorTopic_YN": "N", "meshQualifierList": {"meshQualifier": [{"abbreviation": "CH", "majorTopic_YN": "Y", "qualifierName": "chemistry"}]}}, {"descriptorName": "Menthol", "majorTopic_YN": "N", "meshQualifierList": {"meshQualifier": [{"abbreviation": "CH", "majorTopic_YN": "Y", "qualifierName": "chemistry"}]}}, {"descriptorName": "Ibuprofen", "majorTopic_YN": "N", "meshQualifierList": {"meshQualifier": [{"abbreviation": "CH", "majorTopic_YN": "Y", "qualifierName": "chemistry"}]}}, {"descriptorName": "Anti-Inflammatory Agents, Non-Steroidal", "majorTopic_YN": "N", "meshQualifierList": {"meshQualifier": [{"abbreviation": "CH", "majorTopic_YN": "Y", "qualifierName": "chemistry"}]}}, {"descriptorName": "Gels", "majorTopic_YN": "N"}, {"descriptorName": "Solubility", "majorTopic_YN": "N"}]}, "nihAuthMan": "N", "pageInfo": "179-183", "pmid": "12944138", "pubModel": "Print", "pubTypeList": {"pubType": ["Research Support, Non-U.S. Gov't", "Journal Article"]}, "pubYear": "2003", "publicationStatus": "ppublish", "source": "MED", "subsetList": {"subset": [{"code": "IM", "name": "Index Medicus"}]}, "title": "Improved solubility and in vitro dissolution of Ibuprofen from poloxamer gel using eutectic mixture with menthol."}]}, "version": "6.9"}